examples/__init__.py
examples/crud_use.py
examples/use_own_log_config.py
pymysqldao/__init__.py
pymysqldao/constant_.py
pymysqldao/decorator_.py
pymysqldao/err_.py
pymysqldao/log_controller.py
pymysqldao/mixin_.py
pymysqldao/msg_.py
pymysqldao/crud_/__init__.py
pymysqldao/crud_/create_.py
pymysqldao/crud_/delete_.py
pymysqldao/crud_/retrieve_.py
pymysqldao/crud_/update_.py
pymysql_dao-0.0.11.dist-info/METADATA
pymysql_dao-0.0.11.dist-info/WHEEL
pymysql_dao-0.0.11.dist-info/top_level.txt
pymysql_dao-0.0.11.dist-info/RECORD
