Metadata-Version: 2.1
Name: pymysql-dao
Version: 0.0.11
Summary: A functional enhancement package that focus on crud based PyMySQL
Home-page: https://github.com/ScCcWe/PyMySQLDao
Author: ScCcWe
Author-email: scccwe@163.com
License: "MIT"
Project-URL: Bug Tracker, https://github.com/ScCcWe/PyMySQLDao/issues
Platform: UNKNOWN
Classifier: Programming Language :: Python :: 3
Classifier: Programming Language :: Python :: 3.7
Classifier: Programming Language :: Python :: 3.8
Classifier: Programming Language :: Python :: 3.9
Classifier: License :: OSI Approved :: MIT License
Classifier: Operating System :: OS Independent
Requires-Python: >=3.7
Requires-Dist: PyMySQL
Requires-Dist: pydantic
